Day5/div_by_3.sv
module div_by_3(
    input  logic clk,
    input  logic reset,
    input  logic x_i,
    
    output logic div_o
    );
    
    // Defining the 3 different states as enum
    typedef enum {REM_0, REM_1, REM_2} state_t;
    
    state_t state_curr; // current state value
    state_t state_next; // next state value
    
    always_ff@(posedge clk)
    begin
        if(reset)
            state_curr <= REM_0;
        else
            state_curr <= state_next;   
    end
    
    always_comb begin
        div_o = 1'b0;
        state_next = state_curr;
        case(state_curr)
            REM_0:
                if(x_i)
                    state_next = REM_1;
                else begin
                    state_next = REM_0;
                    div_o = 1'b1;
                end
            REM_1:
                if(x_i) begin
                    state_next = REM_0;
                    div_o = 1'b1;
                end
                else
                    state_next = REM_2;
            REM_2:
                if(x_i)
                    state_next = REM_2;
                else
                    state_next = REM_1;
            default: state_next = REM_0;
        endcase
    end
endmodule

Day5/div_by_3_tb.sv
`timescale 1ns/1ps
//`include "div_by_3.sv"

module div_by_3_tb();
    logic clk, reset, x_i, div_o;

    div_by_3 DUT(.clk(clk), .reset(reset), .x_i(x_i), .div_o(div_o));

    always #5 clk = ~clk;

    initial begin
        clk     = 1'b0;
        x_i     = 1'b0;
        reset   = 1'b1; #8;

        @(posedge clk);
        reset   = 1'b0;

        for (int i = 0; i < 20; i++) begin
            @(posedge clk);            
            x_i = $random % 2;
        end

    #20;
    $finish;
    end

    initial begin
        $dumpfile("div_by_3.vcd");
        $dumpvars(0, div_by_3_tb);
    end

endmodule

Day5/div_by_3.vcd
$date
	Sun Jul 20 14:59:09 2025
$end
$version
	Icarus Verilog
$end
$timescale
	1ps
$end
$scope module div_by_3_tb $end
$var wire 1 ! div_o $end
$var reg 1 " clk $end
$var reg 1 # reset $end
$var reg 1 $ x_i $end
$scope module DUT $end
$var wire 1 " clk $end
$var wire 1 # reset $end
$var wire 1 $ x_i $end
$var reg 1 ! div_o $end
$var integer 32 % state_curr [31:0] $end
$var integer 32 & state_next [31:0] $end
$upscope $end
$scope begin $ivl_for_loop0 $end
$var integer 32 ' i [31:0] $end
$upscope $end
$upscope $end
$enddefinitions $end
$comment Show the parameter values. $end
$dumpall
$end
#0
$dumpvars
b0 '
b0 &
b0 %
0$
1#
0"
1!
$end
#5000
1"
#10000
0"
#15000
0#
1"
#20000
0"
#25000
b1 '
1"
#30000
0"
#35000
b1 &
0!
b10 '
1$
1"
#40000
0"
#45000
1!
b0 &
b1 %
b11 '
1"
#50000
0"
#55000
b1 &
0!
b0 %
b100 '
1"
#60000
0"
#65000
1!
b0 &
b1 %
b101 '
1"
#70000
0"
#75000
b1 &
0!
b0 %
b110 '
1"
#80000
0"
#85000
1!
b0 &
b1 %
b111 '
1"
#90000
0"
#95000
b0 %
b0 &
1!
b1000 '
0$
1"
#100000
0"
#105000
b1 &
0!
b1001 '
1$
1"
#110000
0"
#115000
1!
b0 &
b1 %
b1010 '
1"
#120000
0"
#125000
b0 %
b0 &
1!
b1011 '
0$
1"
#130000
0"
#135000
b1 &
0!
b1100 '
1$
1"
#140000
0"
#145000
1!
b0 &
b1 %
b1101 '
1"
#150000
0"
#155000
b0 %
b0 &
1!
b1110 '
0$
1"
#160000
0"
#165000
b1 &
0!
b1111 '
1$
1"
#170000
0"
#175000
b1 %
0!
b10 &
b10000 '
0$
1"
#180000
0"
#185000
b10 %
0!
b10 &
b10001 '
1$
1"
#190000
0"
#195000
b1 &
b10010 '
0$
1"
#200000
0"
#205000
1!
b1 %
b0 &
b10011 '
1$
1"
#210000
0"
#215000
b1 &
0!
b0 %
b10100 '
1"
#220000
0"
#225000
1!
b0 &
b1 %
1"
#230000
0"
#235000
b1 &
0!
b0 %
1"
